mdf_forge/__init__.py
mdf_forge/forge.py
mdf_forge/version.py
mdf_forge-0.8.0.dist-info/LICENSE
mdf_forge-0.8.0.dist-info/METADATA
mdf_forge-0.8.0.dist-info/NOTICE
mdf_forge-0.8.0.dist-info/WHEEL
mdf_forge-0.8.0.dist-info/top_level.txt
mdf_forge-0.8.0.dist-info/RECORD
